stereoAlign/__init__.py
stereoAlign/alignment.py
stereoAlign/preprocessing.py
stereoAlign/alignment/__init__.py
stereoAlign/alignment/bbknn_alignment.py
stereoAlign/alignment/combat_alignment.py
stereoAlign/alignment/desc_alignment.py
stereoAlign/alignment/harmony_alignment.py
stereoAlign/alignment/mnn_alignment.py
stereoAlign/alignment/scalex_alignment.py
stereoAlign/alignment/scanorama_alignment.py
stereoAlign/alignment/scgen_alignment.py
stereoAlign/alignment/scvi_alignment.py
stereoAlign/alignment/spatialign_alignment.py
stereoAlign/metrics/__init__.py
stereoAlign/metrics/ari.py
stereoAlign/metrics/graph_connectivity.py
stereoAlign/metrics/kbet.py
stereoAlign/metrics/lisi.py
stereoAlign/metrics/silhouette.py
stereoAlign/utils/__init__.py
stereoAlign/utils/check_data.py
stereoAlign/utils/exceptions.py
stereoAlign/utils/get_neighbors.py
stereoAlign/utils/pca_lowrank.py
stereoAlign-0.0.3.dist-info/METADATA
stereoAlign-0.0.3.dist-info/WHEEL
stereoAlign-0.0.3.dist-info/top_level.txt
stereoAlign-0.0.3.dist-info/RECORD
