Metadata-Version: 2.1
Name: stereoAlign
Version: 0.0.3
Summary: A toolkit package of data integration
Author: zhangchao
Author-email: zhangchao5@genomics.cn
Classifier: Programming Language :: Python :: 3
Classifier: License :: OSI Approved :: MIT License
Classifier: Operating System :: OS Independent
Requires-Python: >=3.8
Requires-Dist: matplotlib >=2.2
Requires-Dist: tensorflow
Requires-Dist: scanpy
Requires-Dist: louvain
Requires-Dist: python-igraph
Requires-Dist: h5py
Requires-Dist: pandas
Requires-Dist: numpy
Requires-Dist: scikit-learn
Requires-Dist: harmony-pytorch
Requires-Dist: scanorama
Requires-Dist: scgen
Requires-Dist: scvi-tools
Requires-Dist: mnnpy
Requires-Dist: bbknn
Requires-Dist: desc
